resume_parser/LINKEDIN_SKILLS_ORIGINAL.txt
resume_parser/__init__.py
resume_parser/resumeparse.py
resume_parser/titles_combined.txt
resume_parser/world-universities.csv
resume_parser/__pycache__/__init__.cpython-36.pyc
resume_parser/__pycache__/resume.cpython-36.pyc
resume_parser/__pycache__/resumeparse.cpython-36.pyc
resume_parser/company_working/model/meta.json
resume_parser/company_working/model/tokenizer
resume_parser/company_working/model/ner/cfg
resume_parser/company_working/model/ner/model
resume_parser/company_working/model/ner/moves
resume_parser/company_working/model/vocab/key2row
resume_parser/company_working/model/vocab/lexemes.bin
resume_parser/company_working/model/vocab/strings.json
resume_parser/company_working/model/vocab/vectors
resume_parser/degree/model/meta.json
resume_parser/degree/model/tokenizer
resume_parser/degree/model/ner/cfg
resume_parser/degree/model/ner/model
resume_parser/degree/model/ner/moves
resume_parser/degree/model/vocab/key2row
resume_parser/degree/model/vocab/lexemes.bin
resume_parser/degree/model/vocab/strings.json
resume_parser/degree/model/vocab/vectors
resume_parser-0.8.2.dist-info/LICENSE.txt
resume_parser-0.8.2.dist-info/METADATA
resume_parser-0.8.2.dist-info/WHEEL
resume_parser-0.8.2.dist-info/top_level.txt
resume_parser-0.8.2.dist-info/RECORD
