Metadata-Version: 1.1
Name: resume-parser
Version: 0.8.2
Summary: A resume parser used for extracting information from resumes
Home-page: https://github.com/kbrajwani/resume_parser
Author: kumar
Author-email: kumarrajwani1811@gmail.com
License: MIT
Keywords: resume,parser,cv
Platform: UNKNOWN
Classifier: Development Status :: 3 - Alpha
Classifier: Intended Audience :: Developers
Classifier: Topic :: Software Development :: Build Tools
Classifier: License :: OSI Approved :: MIT License
Classifier: Programming Language :: Python :: 3
Classifier: Programming Language :: Python :: 3.4
Classifier: Programming Language :: Python :: 3.5
Classifier: Programming Language :: Python :: 3.6
